Metadata-Version: 1.1
Name: jira-cache
Version: 0.8.2
Summary: Dump Jira issues to file and reload them without connection to the original server.
Home-page: https://github.com/redtoad/jira-cache
Author: Sebastian Rahlf
Author-email: basti@redtoad.de
License: MIT
Keywords: jira ticket caching json dump
Platform: UNKNOWN
Classifier: Development Status :: 4 - Beta
Classifier: Environment :: Other Environment
Classifier: Intended Audience :: Developers
Classifier: Intended Audience :: Information Technology
Classifier: License :: OSI Approved :: MIT License
Classifier: Operating System :: OS Independent
Classifier: Programming Language :: Python
Classifier: Programming Language :: Python :: 2.7
Classifier: Programming Language :: Python :: 3
Classifier: Programming Language :: Python :: 3.4
Classifier: Programming Language :: Python :: 3.5
